TickerAnalysis/TickerAnalysis.py
TickerAnalysis/__init__.py
ticker_analysis-0.0.1.dist-info/LICENSE
ticker_analysis-0.0.1.dist-info/METADATA
ticker_analysis-0.0.1.dist-info/WHEEL
ticker_analysis-0.0.1.dist-info/top_level.txt
ticker_analysis-0.0.1.dist-info/RECORD
